litestar_utils/__init__.py
litestar_utils/https_redirect.py
litestar_utils/text.py
litestar_utils/timing.py
litestar_utils-0.3.0.dist-info/LICENSE
litestar_utils-0.3.0.dist-info/METADATA
litestar_utils-0.3.0.dist-info/WHEEL
litestar_utils-0.3.0.dist-info/RECORD
