Metadata-Version: 2.1
Name: litestar-utils
Version: 0.3.0
Summary: Utilities for the Litestar framework.
Author: Alessandro Ferrini
Author-email: alessandro.ferrini@apptecsrl.com
Requires-Python: >=3.8,<4.0
Classifier: Programming Language :: Python :: 3
Classifier: Programming Language :: Python :: 3.8
Classifier: Programming Language :: Python :: 3.9
Classifier: Programming Language :: Python :: 3.10
Classifier: Programming Language :: Python :: 3.11
Requires-Dist: litestar
